cspb/CSPB.py
cspb/__init__.py
cspb-1.0.0.dist-info/LICENSE
cspb-1.0.0.dist-info/METADATA
cspb-1.0.0.dist-info/WHEEL
cspb-1.0.0.dist-info/top_level.txt
cspb-1.0.0.dist-info/RECORD
