Metadata-Version: 2.1
Name: cspb
Version: 1.0.0
Summary: CSPB driver package
Home-page: https://github.com/jerry-muir/cspb
Author: Gerard L. Muir
Author-email: jerrymuir65@gmail.com
License: UNKNOWN
Keywords: cluster system power cspb driver raspberry pi
Platform: UNKNOWN
Classifier: License :: OSI Approved :: MIT License
Classifier: Operating System :: POSIX :: Linux
Requires-Python: >=2.7
Requires-Dist: smbus
